jupyterhub_traefik_proxy/__init__.py
jupyterhub_traefik_proxy/consul.py
jupyterhub_traefik_proxy/etcd.py
jupyterhub_traefik_proxy/fileprovider.py
jupyterhub_traefik_proxy/install.py
jupyterhub_traefik_proxy/kv_proxy.py
jupyterhub_traefik_proxy/proxy.py
jupyterhub_traefik_proxy/redis.py
jupyterhub_traefik_proxy/toml.py
jupyterhub_traefik_proxy/traefik_utils.py
jupyterhub_traefik_proxy-2.0.0.dist-info/LICENSE
jupyterhub_traefik_proxy-2.0.0.dist-info/METADATA
jupyterhub_traefik_proxy-2.0.0.dist-info/WHEEL
jupyterhub_traefik_proxy-2.0.0.dist-info/entry_points.txt
jupyterhub_traefik_proxy-2.0.0.dist-info/top_level.txt
jupyterhub_traefik_proxy-2.0.0.dist-info/RECORD
