Metadata-Version: 2.1
Name: jupyterhub-traefik-proxy
Version: 2.0.0
Summary: JupyterHub proxy implementation with traefik
Home-page: https://jupyterhub-traefik-proxy.readthedocs.io
Author: Project Jupyter Contributors
Author-email: jupyter@googlegroups.com
License: BSD
Project-URL: Documentation, https://jupyterhub-traefik-proxy.readthedocs.io
Project-URL: Source, https://github.com/jupyterhub/traefik-proxy/
Project-URL: Tracker, https://github.com/jupyter/traefik-proxy/issues
Keywords: jupyter jupyterhub traefik proxy
Classifier: Intended Audience :: Developers
Classifier: Intended Audience :: System Administrators
Classifier: Intended Audience :: Science/Research
Classifier: License :: OSI Approved :: BSD License
Classifier: Programming Language :: Python
Classifier: Programming Language :: Python :: 3
Requires-Python: >=3.8
License-File: LICENSE
Requires-Dist: aiohttp
Requires-Dist: escapism
Requires-Dist: jupyterhub>=0.9
Requires-Dist: passlib
Requires-Dist: toml
Provides-Extra: consul
Requires-Dist: python-consul2; extra == "consul"
Provides-Extra: etcd
Requires-Dist: etcdpy; extra == "etcd"
Provides-Extra: redis
Requires-Dist: redis; extra == "redis"
Provides-Extra: test
Requires-Dist: jupyterhub-traefik-proxy[consul,etcd,redis,yaml]; extra == "test"
Requires-Dist: certipy; extra == "test"
Requires-Dist: notebook>=4.0; extra == "test"
Requires-Dist: pytest; extra == "test"
Requires-Dist: pytest-asyncio<0.23,>=0.17; extra == "test"
Requires-Dist: pytest-cov; extra == "test"
Requires-Dist: websockets; extra == "test"
Provides-Extra: yaml
Requires-Dist: ruamel.yaml; extra == "yaml"
